coolprompt/__init__.py
coolprompt/assistant.py
coolprompt/data_generator/__init__.py
coolprompt/data_generator/generator.py
coolprompt/data_generator/pydantic_formatters.py
coolprompt/evaluator/__init__.py
coolprompt/evaluator/evaluator.py
coolprompt/evaluator/metrics.py
coolprompt/language_model/__init__.py
coolprompt/language_model/deepeval_model.py
coolprompt/language_model/llm.py
coolprompt/optimizer/__init__.py
coolprompt/optimizer/distill_prompt/__init__.py
coolprompt/optimizer/distill_prompt/candidate.py
coolprompt/optimizer/distill_prompt/distiller.py
coolprompt/optimizer/distill_prompt/generate.py
coolprompt/optimizer/distill_prompt/run.py
coolprompt/optimizer/distill_prompt/utils.py
coolprompt/optimizer/hype/__init__.py
coolprompt/optimizer/hype/hype.py
coolprompt/optimizer/reflective_prompt/__init__.py
coolprompt/optimizer/reflective_prompt/evoluter.py
coolprompt/optimizer/reflective_prompt/prompt.py
coolprompt/optimizer/reflective_prompt/run.py
coolprompt/prompt_assistant/__init__.py
coolprompt/prompt_assistant/prompt_assistant.py
coolprompt/task_detector/__init__.py
coolprompt/task_detector/detector.py
coolprompt/task_detector/pydantic_formatters.py
coolprompt/utils/__init__.py
coolprompt/utils/arithmetics.py
coolprompt/utils/default.py
coolprompt/utils/enums.py
coolprompt/utils/language_detection.py
coolprompt/utils/logging_config.py
coolprompt/utils/parsing.py
coolprompt/utils/var_validation.py
coolprompt/utils/correction/__init__.py
coolprompt/utils/correction/corrector.py
coolprompt/utils/correction/rule.py
coolprompt/utils/prompt_templates/__init__.py
coolprompt/utils/prompt_templates/assistant_templates.py
coolprompt/utils/prompt_templates/basic_methods_templates.py
coolprompt/utils/prompt_templates/correction_templates.py
coolprompt/utils/prompt_templates/data_generator_templates.py
coolprompt/utils/prompt_templates/default_templates.py
coolprompt/utils/prompt_templates/distillprompt_templates.py
coolprompt-1.2.1.dist-info/licenses/LICENSE
coolprompt-1.2.1.dist-info/METADATA
coolprompt-1.2.1.dist-info/WHEEL
coolprompt-1.2.1.dist-info/top_level.txt
coolprompt-1.2.1.dist-info/RECORD
