Metadata-Version: 2.4
Name: coolprompt
Version: 1.2.1
Summary: Framework for automative prompting creation and optimization
Author-email: Nikita Kulin <serito1998@gmail.com>, Artur Khairullin <anderbrine05@gmail.com>, Alena Sitkina <sitkina.alena2017@yandex.ru>, Ernest Dyagin <tsenred@yandex.com>, Viktor Zhuravlev <viktor.zhuravlev1919@gmail.com>
Maintainer-email: Nikita Kulin <serito1998@gmail.com>
License-Expression: Apache-2.0
Project-URL: Homepage, https://github.com/CTLab-ITMO/CoolPrompt
Project-URL: Issues, https://github.com/CTLab-ITMO/CoolPrompt/issues
Project-URL: Documentation, https://github.com/CTLab-ITMO/CoolPrompt
Project-URL: Repository, https://github.com/CTLab-ITMO/CoolPrompt
Project-URL: Changelog, https://github.com/CTLab-ITMO/CoolPrompt/blob/master/CHANGELOG.md
Keywords: prompting,autoprompting,llm,transformers,prompt-engineering
Classifier: Programming Language :: Python :: 3
Classifier: Programming Language :: Python :: 3.10
Classifier: Programming Language :: Python :: 3.11
Classifier: Programming Language :: Python :: 3.12
Classifier: Programming Language :: Python :: 3.13
Classifier: Operating System :: OS Independent
Requires-Python: >=3.12
License-File: LICENSE
Requires-Dist: accelerate>=1.10.0
Requires-Dist: bert-score>=0.3.0
Requires-Dist: evaluate>=0.4.0
Requires-Dist: tqdm>=4.67.0
Requires-Dist: urllib3>=2.3.0
Requires-Dist: nltk>=3.9.0
Requires-Dist: dirtyjson>=1.0.0
Requires-Dist: rouge_score>=0.1.2
Requires-Dist: scikit-learn>=1.6.0
Requires-Dist: langchain>=0.3.0
Requires-Dist: langchain-community>=0.3.0
Requires-Dist: langchain-core>=0.3.0
Requires-Dist: langchain_huggingface>=0.3.0
Requires-Dist: langchain-openai>=0.3.0
Requires-Dist: langdetect>=0.4.0
Requires-Dist: deepeval>=3.7.2
Dynamic: license-file
